simplemseed/__init__.py
simplemseed/bandcode.json
simplemseed/exceptions.py
simplemseed/fdsnsourceid.py
simplemseed/miniseed.py
simplemseed/mseed2details.py
simplemseed/mseed2to3.py
simplemseed/mseed3.py
simplemseed/mseed3details.py
simplemseed/mseed3merge.py
simplemseed/py.typed
simplemseed/seedcodec.py
simplemseed/sourcecode.json
simplemseed/steim1.py
simplemseed/steim2.py
simplemseed/steimframeblock.py
simplemseed/util.py
simplemseed/version.py
simplemseed-1.0.1.dist-info/METADATA
simplemseed-1.0.1.dist-info/WHEEL
simplemseed-1.0.1.dist-info/entry_points.txt
simplemseed-1.0.1.dist-info/licenses/LICENSE
simplemseed-1.0.1.dist-info/RECORD
