Metadata-Version: 2.4
Name: simplemseed
Version: 1.0.1
Summary: miniseed3 in pure python
Project-URL: Homepage, https://github.com/crotwell/simplemseed
Project-URL: Documentation, https://simplemseed.readthedocs.io/en/latest/
Project-URL: Repository, https://github.com/crotwell/simplemseed
Project-URL: Issues, https://github.com/crotwell/simplemseed/issues
Author-email: Philip Crotwell <crotwell@seis.sc.edu>
License-File: LICENSE
Keywords: fdsn,miniseed,miniseed3,seed,sourceid,steim1,steim2
Classifier: License :: OSI Approved :: GNU Lesser General Public License v2 or later (LGPLv2+)
Classifier: Operating System :: OS Independent
Classifier: Programming Language :: Python :: 3
Requires-Python: >=3.10
Requires-Dist: crc32c
Requires-Dist: jsonpointer
Requires-Dist: numpy
